[
    {
        "name": "Visiting Schönbrunn Palace",
        "category": "History",
        "score": 5,
        "description": "Explore the magnificent Schönbrunn Palace, a cultural treasure and UNESCO World Heritage Site in Vienna.",
        "city": "Vienna",
        "longitude": 16.3119,
        "latitude": 48.1845,
        "cost": "$$"
    },
    {
        "name": "Skiing in Tyrol",
        "category": "Adventure",
        "score": 5,
        "description": "Experience world-class skiing in the stunning Alpine landscape of Tyrol, a premier winter sports destination.",
        "city": "Innsbruck",
        "longitude": 11.4041,
        "latitude": 47.2692,
        "cost": "$$$"
    },
    {
        "name": "Exploring Salzburg's Old Town",
        "category": "Culture",
        "score": 4,
        "description": "Discover the historic charm of Salzburg's Old Town, the birthplace of Mozart and a UNESCO World Heritage site.",
        "city": "Salzburg",
        "longitude": 13.0430,
        "latitude": 47.8095,
        "cost": "$$"
    },
    {
        "name": "Touring the Vienna State Opera",
        "category": "Culture",
        "score": 5,
        "description": "Take a guided tour of the Vienna State Opera, an iconic institution and architectural masterpiece.",
        "city": "Vienna",
        "longitude": 16.3721,
        "latitude": 48.2031,
        "cost": "$$"
    },
    {
        "name": "Hiking in the Austrian Alps",
        "category": "Nature",
        "score": 4,
        "description": "Embark on a scenic hike through the Austrian Alps, known for their breathtaking beauty and diverse trails.",
        "city": "Zell am See",
        "longitude": 12.7969,
        "latitude": 47.3235,
        "cost": "$$"
    },
    {
        "name": "Exploring Hallstatt",
        "category": "Leisure",
        "score": 4,
        "description": "Visit the picturesque village of Hallstatt, a stunning lakeside town that's like stepping into a fairy-tale.",
        "city": "Hallstatt",
        "longitude": 13.6493,
        "latitude": 47.5622,
        "cost": "$$"
    },
    {
        "name": "Wine Tasting in Wachau Valley",
        "category": "Gastronomy",
        "score": 3,
        "description": "Enjoy a wine tasting experience in the Wachau Valley, renowned for its high-quality white wines and beautiful scenery.",
        "city": "Krems",
        "longitude": 15.5988,
        "latitude": 48.4092,
        "cost": "$$"
    },
    {
        "name": "Visiting the Hofburg Imperial Palace",
        "category": "History",
        "score": 5,
        "description": "Explore the Hofburg Imperial Palace in Vienna, a historic complex that was the residence of the Habsburgs for centuries.",
        "city": "Vienna",
        "longitude": 16.3656,
        "latitude": 48.2077,
        "cost": "$$"
    },
    {
        "name": "Cycling around Lake Constance",
        "category": "Adventure",
        "score": 3,
        "description": "Cycle around the beautiful Lake Constance, enjoying scenic views and charming towns along the way.",
        "city": "Bregenz",
        "longitude": 9.7489,
        "latitude": 47.5031,
        "cost": "$"
    },
    {
        "name": "Attending the Salzburg Festival",
        "category": "Culture",
        "score": 5,
        "description": "Experience the world-famous Salzburg Festival, a celebration of music and drama in the historic city of Salzburg.",
        "city": "Salzburg",
        "longitude": 13.0550,
        "latitude": 47.8021,
        "cost": "$$$"
    }
]
